examples/layout_geom_reggrid/run_pymoo.py
examples/layout_geom_reggrids/run_pymoo.py
examples/layout_regular_grid/run_gg.py
examples/layout_regular_grid/run_pymoo.py
examples/layout_single_state/run_gg.py
examples/layout_single_state/run_pymoo.py
examples/layout_wind_rose/run_gg.py
examples/layout_wind_rose/run_pymoo.py
examples/wake_steering/run_gg.py
examples/wake_steering/run_pymoo.py
foxes_opt/__init__.py
foxes_opt/constraints/__init__.py
foxes_opt/constraints/area_geometry.py
foxes_opt/constraints/min_dist.py
foxes_opt/core/__init__.py
foxes_opt/core/farm_constraint.py
foxes_opt/core/farm_objective.py
foxes_opt/core/farm_opt_problem.py
foxes_opt/core/farm_vars_problem.py
foxes_opt/input/__init__.py
foxes_opt/input/yaml/__init__.py
foxes_opt/input/yaml/dict.py
foxes_opt/input/yaml/yaml.py
foxes_opt/objectives/__init__.py
foxes_opt/objectives/farm_vars.py
foxes_opt/objectives/max_n_turbines.py
foxes_opt/output/__init__.py
foxes_opt/output/opt_output.py
foxes_opt/output/results_writer.py
foxes_opt/problems/__init__.py
foxes_opt/problems/opt_farm_vars.py
foxes_opt/problems/layout/__init__.py
foxes_opt/problems/layout/farm_layout.py
foxes_opt/problems/layout/regular_layout.py
foxes_opt/problems/layout/geom_layouts/__init__.py
foxes_opt/problems/layout/geom_layouts/constraints.py
foxes_opt/problems/layout/geom_layouts/geom_reggrid.py
foxes_opt/problems/layout/geom_layouts/geom_reggrids.py
foxes_opt/problems/layout/geom_layouts/objectives.py
foxes_opt-0.7.0.dist-info/licenses/LICENSE
scratch/examples/layout_regular_grids/run_pymoo.py
scratch/problems/geom_layout.py
scratch/problems/geom_layout_gridded.py
scratch/problems/reggrids_layout.py
tests/00_layout_single_state/test_layout_single_state.py
foxes_opt-0.7.0.dist-info/METADATA
foxes_opt-0.7.0.dist-info/WHEEL
foxes_opt-0.7.0.dist-info/entry_points.txt
foxes_opt-0.7.0.dist-info/top_level.txt
foxes_opt-0.7.0.dist-info/RECORD
