Metadata-Version: 2.4
Name: foxes-opt
Version: 0.7.0
Summary: Wind farm optimization for the FOXES package
Author: Jonas Schulte
Maintainer: Jonas Schulte
License: MIT License
Project-URL: Homepage, https://github.com/FraunhoferIWES/foxes-opt
Project-URL: Documentation, https://fraunhoferiwes.github.io/foxes-opt/index.html
Project-URL: Repository, https://github.com/FraunhoferIWES/foxes-opt.git
Project-URL: Bug Tracker, https://github.com/FraunhoferIWES/foxes-opt/issues
Project-URL: Changelog, https://github.com/FraunhoferIWES/foxes-opt/blob/main/CHANGELOG.md
Keywords: Wind farm,Wake modelling,Wind farm optimization
Classifier: Topic :: Scientific/Engineering
Classifier: Intended Audience :: Developers
Classifier: Intended Audience :: Science/Research
Classifier: Programming Language :: Python :: 3
Classifier: Programming Language :: Python :: 3.9
Classifier: Programming Language :: Python :: 3.10
Classifier: Programming Language :: Python :: 3.11
Classifier: Programming Language :: Python :: 3.12
Classifier: Programming Language :: Python :: 3.13
Classifier: License :: OSI Approved :: MIT License
Classifier: Operating System :: OS Independent
Classifier: Development Status :: 4 - Beta
Requires-Python: >=3.9
License-File: LICENSE
Requires-Dist: foxes>=1.7.1
Requires-Dist: iwopy>=0.3.1
Requires-Dist: pymoo>=0.6
Requires-Dist: xarray>=2023.9
Requires-Dist: netcdf4>=1.7
Provides-Extra: doc
Requires-Dist: setuptools>=61.0; extra == "doc"
Requires-Dist: sphinx>=5.0; extra == "doc"
Requires-Dist: sphinx-immaterial>=0.10; extra == "doc"
Requires-Dist: myst-nb>=0.1; extra == "doc"
Requires-Dist: ipykernel>=5.0; extra == "doc"
Requires-Dist: ipywidgets>=5.0; extra == "doc"
Requires-Dist: m2r2>=0.2; extra == "doc"
Requires-Dist: lxml_html_clean>=0.4; extra == "doc"
Provides-Extra: test
Requires-Dist: pytest>=7.0; extra == "test"
Requires-Dist: nbmake>1.0; extra == "test"
Provides-Extra: dev
Requires-Dist: pre-commit>=0.1; extra == "dev"
Requires-Dist: objsize>=0.5; extra == "dev"
Requires-Dist: jupyter>=1.0; extra == "dev"
Dynamic: license-file
